{
    "error-coord": [
        {
            "x-coord": 31,
            "y-coord": 35,
            "errx-ble": 2.4681029851456433,
            "erry-ble": 3.3478682300954525,
            "err-ble": 4.1592973001899365
        },
        {
            "x-coord": 11,
            "y-coord": 31,
            "errx-ble": 2.4978734786250767,
            "erry-ble": 2.7874094503481754,
            "err-ble": 3.74286298962557
        },
        {
            "x-coord": 23,
            "y-coord": 19,
            "errx-ble": 1.0331630775801113,
            "erry-ble": 0.7161835961393145,
            "err-ble": 1.2571176906932175
        },
        {
            "x-coord": 23,
            "y-coord": 7,
            "errx-ble": 0.9294194988135778,
            "erry-ble": 2.8844851253625587,
            "err-ble": 3.030523889233137
        },
        {
            "x-coord": 27,
            "y-coord": 15,
            "errx-ble": 1.9150846227598723,
            "erry-ble": 1.2024604732134796,
            "err-ble": 2.2612961552994575
        },
        {
            "x-coord": 15,
            "y-coord": 15,
            "errx-ble": 0.7919995427392301,
            "erry-ble": 1.455131167217815,
            "err-ble": 1.6567045570975625
        },
        {
            "x-coord": 11,
            "y-coord": 19,
            "errx-ble": 1.749987098054493,
            "erry-ble": 0.5523753491775857,
            "err-ble": 1.8350949211788052
        },
        {
            "x-coord": 31,
            "y-coord": 17,
            "errx-ble": 2.4519300403244473,
            "erry-ble": 0.7864504958630704,
            "err-ble": 2.574968991092653
        },
        {
            "x-coord": 7,
            "y-coord": 5,
            "errx-ble": 3.231698020851869,
            "erry-ble": 3.0555015788626827,
            "err-ble": 4.447466919091162
        },
        {
            "x-coord": 15,
            "y-coord": 3,
            "errx-ble": 0.6903121436103717,
            "erry-ble": 3.8988354585602494,
            "err-ble": 3.959475822447039
        },
        {
            "x-coord": 31,
            "y-coord": 11,
            "errx-ble": 2.507730472714556,
            "erry-ble": 1.78215882104781,
            "err-ble": 3.076491863668697
        },
        {
            "x-coord": 11,
            "y-coord": 7,
            "errx-ble": 1.7365717582853588,
            "erry-ble": 2.6579985831053596,
            "err-ble": 3.1750020377102754
        },
        {
            "x-coord": 3,
            "y-coord": 21,
            "errx-ble": 4.561034456616253,
            "erry-ble": 0.8332978743585062,
            "err-ble": 4.636531102219753
        },
        {
            "x-coord": 23,
            "y-coord": 25,
            "errx-ble": 1.210233002544864,
            "erry-ble": 0.8284714366685282,
            "err-ble": 1.4666386200507513
        },
        {
            "x-coord": 15,
            "y-coord": 21,
            "errx-ble": 1.15414199203922,
            "erry-ble": 0.4623576588874172,
            "err-ble": 1.2433094315254396
        },
        {
            "x-coord": 23,
            "y-coord": 13,
            "errx-ble": 0.778207624633244,
            "erry-ble": 2.0989868613733513,
            "err-ble": 2.2386051351802236
        },
        {
            "x-coord": 31,
            "y-coord": 23,
            "errx-ble": 2.7052300538131733,
            "erry-ble": 0.46462499257275663,
            "err-ble": 2.744839891100619
        },
        {
            "x-coord": 31,
            "y-coord": 29,
            "errx-ble": 2.7622608460446316,
            "erry-ble": 1.977782260904635,
            "err-ble": 3.3973088839757053
        },
        {
            "x-coord": 35,
            "y-coord": 31,
            "errx-ble": 3.964304725037465,
            "erry-ble": 2.3091356179743636,
            "err-ble": 4.587790236611981
        },
        {
            "x-coord": 7,
            "y-coord": 23,
            "errx-ble": 2.3944149940176196,
            "erry-ble": 0.3206861665091722,
            "err-ble": 2.4157944409586563
        },
        {
            "x-coord": 27,
            "y-coord": 21,
            "errx-ble": 1.9489772504204548,
            "erry-ble": 0.4745558794675524,
            "err-ble": 2.005920139335985
        },
        {
            "x-coord": 3,
            "y-coord": 9,
            "errx-ble": 3.5709356333120708,
            "erry-ble": 2.709772031136211,
            "err-ble": 4.482682875018703
        },
        {
            "x-coord": 19,
            "y-coord": 11,
            "errx-ble": 0.17662066496075218,
            "erry-ble": 2.5424814543003076,
            "err-ble": 2.548608797903708
        },
        {
            "x-coord": 31,
            "y-coord": 5,
            "errx-ble": 2.9089431816146982,
            "erry-ble": 3.4534983585794454,
            "err-ble": 4.515373887794184
        },
        {
            "x-coord": 19,
            "y-coord": 29,
            "errx-ble": 0.3001906339330393,
            "erry-ble": 1.9405291460682597,
            "err-ble": 1.9636109042887109
        },
        {
            "x-coord": 27,
            "y-coord": 3,
            "errx-ble": 1.9168758501186562,
            "erry-ble": 4.082903283193001,
            "err-ble": 4.510489135856145
        },
        {
            "x-coord": 7,
            "y-coord": 11,
            "errx-ble": 2.4768848369696173,
            "erry-ble": 2.1650840423427473,
            "err-ble": 3.2897640350057356
        },
        {
            "x-coord": 27,
            "y-coord": 33,
            "errx-ble": 1.9036536854756232,
            "erry-ble": 2.4436614057976422,
            "err-ble": 3.097640782984662
        },
        {
            "x-coord": 11,
            "y-coord": 13,
            "errx-ble": 1.4917002938762896,
            "erry-ble": 1.4809652176676162,
            "err-ble": 2.1020056476355857
        },
        {
            "x-coord": 7,
            "y-coord": 29,
            "errx-ble": 3.048119767507606,
            "erry-ble": 2.216523510043159,
            "err-ble": 3.7688208484411496
        },
        {
            "x-coord": 35,
            "y-coord": 19,
            "errx-ble": 3.743999334292301,
            "erry-ble": 0.3280190461331422,
            "err-ble": 3.7583410582073693
        },
        {
            "x-coord": 7,
            "y-coord": 17,
            "errx-ble": 2.516887783201409,
            "erry-ble": 1.0088376759921989,
            "err-ble": 2.7115452365265535
        },
        {
            "x-coord": 35,
            "y-coord": 7,
            "errx-ble": 3.7206493396457634,
            "erry-ble": 3.1026661207390447,
            "err-ble": 4.844560719548092
        },
        {
            "x-coord": 19,
            "y-coord": 35,
            "errx-ble": 0.40615077054627235,
            "erry-ble": 3.4400885815165854,
            "err-ble": 3.4639815093467403
        },
        {
            "x-coord": 23,
            "y-coord": 31,
            "errx-ble": 0.9315398664954564,
            "erry-ble": 1.9601579092747232,
            "err-ble": 2.1702501128124903
        },
        {
            "x-coord": 19,
            "y-coord": 5,
            "errx-ble": 0.3997897698825465,
            "erry-ble": 3.039732646749264,
            "err-ble": 3.0659103743938805
        },
        {
            "x-coord": 7,
            "y-coord": 35,
            "errx-ble": 3.3265460961737596,
            "erry-ble": 3.8420231427240235,
            "err-ble": 5.082032148579529
        },
        {
            "x-coord": 11,
            "y-coord": 25,
            "errx-ble": 1.962253229984287,
            "erry-ble": 0.584271480856373,
            "err-ble": 2.0473912430031214
        },
        {
            "x-coord": 15,
            "y-coord": 33,
            "errx-ble": 1.0317069162945354,
            "erry-ble": 2.578186395416159,
            "err-ble": 2.776952331358777
        }
    ],
    "mae-ble": 3.079820581204917,
    "rmse-ble-x": 2.3199825967594787,
    "rmse-ble-y": 2.288301330134471,
    "max-error-ble": 5.082032148579529,
    "min-error-ble": 1.2433094315254396,
    "k": 15,
    "fd": 9,
    "filter": "movingAverage"
}