{
    "error-coord": [
        {
            "x-coord": 31,
            "y-coord": 35,
            "errx-ble": 1.8263735086641477,
            "erry-ble": 3.3635074278873938,
            "err-ble": 3.8273780072791164
        },
        {
            "x-coord": 11,
            "y-coord": 31,
            "errx-ble": 2.140374603066565,
            "erry-ble": 3.0710501384323607,
            "err-ble": 3.743334395190707
        },
        {
            "x-coord": 23,
            "y-coord": 19,
            "errx-ble": 0.8444567966513812,
            "erry-ble": 1.247250299447839,
            "err-ble": 1.5062339097508846
        },
        {
            "x-coord": 23,
            "y-coord": 7,
            "errx-ble": 1.0196151758744687,
            "erry-ble": 2.45473958527027,
            "err-ble": 2.658074780431578
        },
        {
            "x-coord": 27,
            "y-coord": 15,
            "errx-ble": 1.9492683393270047,
            "erry-ble": 0.4900563071292044,
            "err-ble": 2.0099259296948664
        },
        {
            "x-coord": 15,
            "y-coord": 15,
            "errx-ble": 0.7600305759174837,
            "erry-ble": 1.0843203166759259,
            "err-ble": 1.3241589879941313
        },
        {
            "x-coord": 11,
            "y-coord": 19,
            "errx-ble": 1.660008089317565,
            "erry-ble": 0.24363433808802454,
            "err-ble": 1.6777915684897642
        },
        {
            "x-coord": 31,
            "y-coord": 17,
            "errx-ble": 2.295212147962202,
            "erry-ble": 1.529167061753288,
            "err-ble": 2.757961331655041
        },
        {
            "x-coord": 7,
            "y-coord": 5,
            "errx-ble": 2.700599878602364,
            "erry-ble": 2.4055454654668598,
            "err-ble": 3.616612875431275
        },
        {
            "x-coord": 15,
            "y-coord": 3,
            "errx-ble": 0.8114347003725523,
            "erry-ble": 2.9645611604305246,
            "err-ble": 3.073605236022003
        },
        {
            "x-coord": 31,
            "y-coord": 11,
            "errx-ble": 2.1353384208640875,
            "erry-ble": 1.8383893173190884,
            "err-ble": 2.817684413423774
        },
        {
            "x-coord": 11,
            "y-coord": 7,
            "errx-ble": 1.4625639049768921,
            "erry-ble": 2.027979315987961,
            "err-ble": 2.500358630720052
        },
        {
            "x-coord": 3,
            "y-coord": 21,
            "errx-ble": 4.396976956277864,
            "erry-ble": 1.2232585288199416,
            "err-ble": 4.563964042624489
        },
        {
            "x-coord": 23,
            "y-coord": 25,
            "errx-ble": 1.0918379268155365,
            "erry-ble": 0.23071706894947466,
            "err-ble": 1.1159482175878437
        },
        {
            "x-coord": 15,
            "y-coord": 21,
            "errx-ble": 0.8859619222569826,
            "erry-ble": 0.0012926573048542167,
            "err-ble": 0.885962865278334
        },
        {
            "x-coord": 23,
            "y-coord": 13,
            "errx-ble": 0.6047817413644797,
            "erry-ble": 2.341121395117579,
            "err-ble": 2.4179764972731084
        },
        {
            "x-coord": 31,
            "y-coord": 23,
            "errx-ble": 1.9612269872206713,
            "erry-ble": 0.1322181984191957,
            "err-ble": 1.965678749795065
        },
        {
            "x-coord": 31,
            "y-coord": 29,
            "errx-ble": 1.5679479800696685,
            "erry-ble": 1.221403792713977,
            "err-ble": 1.9875331677888148
        },
        {
            "x-coord": 35,
            "y-coord": 31,
            "errx-ble": 3.4272997331353245,
            "erry-ble": 2.1556649646689943,
            "err-ble": 4.048860938665447
        },
        {
            "x-coord": 7,
            "y-coord": 23,
            "errx-ble": 1.8175124055723357,
            "erry-ble": 0.2039625336665722,
            "err-ble": 1.828921009652693
        },
        {
            "x-coord": 27,
            "y-coord": 21,
            "errx-ble": 1.7885317589005523,
            "erry-ble": 0.02473410844857895,
            "err-ble": 1.7887027781933613
        },
        {
            "x-coord": 3,
            "y-coord": 9,
            "errx-ble": 3.343740189655188,
            "erry-ble": 1.9302820565669474,
            "err-ble": 3.8609049811954237
        },
        {
            "x-coord": 19,
            "y-coord": 11,
            "errx-ble": 0.29569292500779515,
            "erry-ble": 2.192340074227116,
            "err-ble": 2.212191064750471
        },
        {
            "x-coord": 31,
            "y-coord": 5,
            "errx-ble": 2.6799305563224856,
            "erry-ble": 2.8154228410617876,
            "err-ble": 3.886982577872375
        },
        {
            "x-coord": 19,
            "y-coord": 29,
            "errx-ble": 0.5171506667942491,
            "erry-ble": 0.9531446446327809,
            "err-ble": 1.084402842931485
        },
        {
            "x-coord": 27,
            "y-coord": 3,
            "errx-ble": 1.8076801186066105,
            "erry-ble": 2.965117971558592,
            "err-ble": 3.47269808599385
        },
        {
            "x-coord": 7,
            "y-coord": 11,
            "errx-ble": 2.4284377130194295,
            "erry-ble": 1.8722014556956406,
            "err-ble": 3.066341144870204
        },
        {
            "x-coord": 27,
            "y-coord": 33,
            "errx-ble": 1.5109708827870612,
            "erry-ble": 1.707814375973858,
            "err-ble": 2.2802769462092294
        },
        {
            "x-coord": 11,
            "y-coord": 13,
            "errx-ble": 1.4204229734088096,
            "erry-ble": 1.4699499352999605,
            "err-ble": 2.0441023055796115
        },
        {
            "x-coord": 7,
            "y-coord": 29,
            "errx-ble": 2.7590123504088955,
            "erry-ble": 1.4090948148469227,
            "err-ble": 3.0980150656407885
        },
        {
            "x-coord": 35,
            "y-coord": 19,
            "errx-ble": 3.828751839654103,
            "erry-ble": 0.09646435172613614,
            "err-ble": 3.8299668433040805
        },
        {
            "x-coord": 7,
            "y-coord": 17,
            "errx-ble": 2.3592947293047644,
            "erry-ble": 0.6735339972085036,
            "err-ble": 2.453552458196259
        },
        {
            "x-coord": 35,
            "y-coord": 7,
            "errx-ble": 3.2321171646243205,
            "erry-ble": 2.9904551087077165,
            "err-ble": 4.4033399963045365
        },
        {
            "x-coord": 19,
            "y-coord": 35,
            "errx-ble": 0.7884326297721621,
            "erry-ble": 3.1649596104285025,
            "err-ble": 3.2616859670012968
        },
        {
            "x-coord": 23,
            "y-coord": 31,
            "errx-ble": 0.12167980312268013,
            "erry-ble": 1.4495652802905152,
            "err-ble": 1.4546633549765713
        },
        {
            "x-coord": 19,
            "y-coord": 5,
            "errx-ble": 0.34143180893444264,
            "erry-ble": 2.6508116497756893,
            "err-ble": 2.6727098762751558
        },
        {
            "x-coord": 7,
            "y-coord": 35,
            "errx-ble": 3.209000824073188,
            "erry-ble": 3.453026564742824,
            "err-ble": 4.713923922351953
        },
        {
            "x-coord": 11,
            "y-coord": 25,
            "errx-ble": 1.3573667109039709,
            "erry-ble": 0.8306402732646735,
            "err-ble": 1.5913540308301846
        },
        {
            "x-coord": 15,
            "y-coord": 33,
            "errx-ble": 1.1451964449059016,
            "erry-ble": 1.5092194143984723,
            "err-ble": 1.8945231954828061
        }
    ],
    "mae-ble": 2.6512385382745807,
    "rmse-ble-x": 2.073166080000514,
    "rmse-ble-y": 1.9454440047960966,
    "max-error-ble": 4.713923922351953,
    "min-error-ble": 0.885962865278334,
    "k": 11,
    "fd": 9,
    "filter": "movingAverage"
}