{
    "error-coord": [
        {
            "x-coord": 19,
            "y-coord": 34,
            "errx-ble": 1.5525765176641741,
            "erry-ble": 4.202049928411646,
            "err-ble": 4.479700597592046
        },
        {
            "x-coord": 25,
            "y-coord": 26,
            "errx-ble": 3.5450985145379463,
            "erry-ble": 1.161507339255976,
            "err-ble": 3.7305258043504606
        },
        {
            "x-coord": 19,
            "y-coord": 18,
            "errx-ble": 1.7818817768918678,
            "erry-ble": 1.5880231875957356,
            "err-ble": 2.386822220267157
        },
        {
            "x-coord": 25,
            "y-coord": 2,
            "errx-ble": 3.6133341997009727,
            "erry-ble": 5.569126924558342,
            "err-ble": 6.638626269083787
        },
        {
            "x-coord": 1,
            "y-coord": 26,
            "errx-ble": 3.558118741803848,
            "erry-ble": 1.3140445543261523,
            "err-ble": 3.793009632406701
        },
        {
            "x-coord": 19,
            "y-coord": 26,
            "errx-ble": 1.3420031861792883,
            "erry-ble": 0.6289807859631554,
            "err-ble": 1.4820895319872514
        },
        {
            "x-coord": 7,
            "y-coord": 10,
            "errx-ble": 1.570838080726203,
            "erry-ble": 2.6732615913682607,
            "err-ble": 3.1006224877827915
        },
        {
            "x-coord": 13,
            "y-coord": 2,
            "errx-ble": 0.3136609456724038,
            "erry-ble": 3.88374669815558,
            "err-ble": 3.896392126605647
        },
        {
            "x-coord": 25,
            "y-coord": 34,
            "errx-ble": 3.559448841962574,
            "erry-ble": 3.2928725604772113,
            "err-ble": 4.848988116926299
        },
        {
            "x-coord": 7,
            "y-coord": 18,
            "errx-ble": 1.3969036956906162,
            "erry-ble": 1.5318234858334716,
            "err-ble": 2.0731191781431932
        },
        {
            "x-coord": 1,
            "y-coord": 2,
            "errx-ble": 3.5639449526464606,
            "erry-ble": 5.135711623299891,
            "err-ble": 6.251178889072987
        },
        {
            "x-coord": 7,
            "y-coord": 34,
            "errx-ble": 2.095600240098522,
            "erry-ble": 3.362416064191486,
            "err-ble": 3.9619921952262787
        },
        {
            "x-coord": 1,
            "y-coord": 10,
            "errx-ble": 3.2524649769231875,
            "erry-ble": 3.2396765069589852,
            "err-ble": 4.590646174108164
        },
        {
            "x-coord": 19,
            "y-coord": 40,
            "errx-ble": 1.6751629991546175,
            "erry-ble": 5.724137896628151,
            "err-ble": 5.964220463174651
        },
        {
            "x-coord": 25,
            "y-coord": 10,
            "errx-ble": 3.2360603011189526,
            "erry-ble": 3.060375168370036,
            "err-ble": 4.453985007120479
        },
        {
            "x-coord": 19,
            "y-coord": 10,
            "errx-ble": 1.7786053582087038,
            "erry-ble": 2.8461536212946275,
            "err-ble": 3.3561924045348226
        },
        {
            "x-coord": 1,
            "y-coord": 34,
            "errx-ble": 3.7951645534571505,
            "erry-ble": 3.8727250121021872,
            "err-ble": 5.422294072362684
        },
        {
            "x-coord": 13,
            "y-coord": 18,
            "errx-ble": 0.15346901085079434,
            "erry-ble": 1.5056286288446064,
            "err-ble": 1.5134299803056666
        },
        {
            "x-coord": 7,
            "y-coord": 40,
            "errx-ble": 2.4327812992719586,
            "erry-ble": 3.9905261883762098,
            "err-ble": 4.673620022017593
        },
        {
            "x-coord": 7,
            "y-coord": 26,
            "errx-ble": 1.6939444563975832,
            "erry-ble": 2.2518645429017465,
            "err-ble": 2.8178611997290064
        },
        {
            "x-coord": 13,
            "y-coord": 26,
            "errx-ble": 0.18816267696336036,
            "erry-ble": 0.4762467893532889,
            "err-ble": 0.5120705003916295
        }
    ],
    "mae-ble": 3.807018422532824,
    "rmse-ble-x": 2.4901825176101164,
    "rmse-ble-y": 3.287646397848893,
    "max-error-ble": 6.638626269083787,
    "min-error-ble": 0.5120705003916295,
    "k": 9,
    "fd": 5,
    "filter": "raw"
}