{
    "error-coord": [
        {
            "x-coord": 19,
            "y-coord": 34,
            "errx-ble": 1.1939770526919857,
            "erry-ble": 5.231484149674495,
            "err-ble": 5.366004809040942
        },
        {
            "x-coord": 25,
            "y-coord": 26,
            "errx-ble": 3.6590063422242722,
            "erry-ble": 1.7720021163497173,
            "err-ble": 4.065503525122727
        },
        {
            "x-coord": 19,
            "y-coord": 18,
            "errx-ble": 1.8152348429414136,
            "erry-ble": 1.1070405982122813,
            "err-ble": 2.126174127657174
        },
        {
            "x-coord": 25,
            "y-coord": 2,
            "errx-ble": 3.6571500831444084,
            "erry-ble": 3.174627085608669,
            "err-ble": 4.842830150162541
        },
        {
            "x-coord": 1,
            "y-coord": 26,
            "errx-ble": 2.7873393820980743,
            "erry-ble": 2.8244277241912514,
            "err-ble": 3.968205236649819
        },
        {
            "x-coord": 19,
            "y-coord": 26,
            "errx-ble": 0.7430194478389914,
            "erry-ble": 0.8602190596622776,
            "err-ble": 1.1366858539074078
        },
        {
            "x-coord": 7,
            "y-coord": 10,
            "errx-ble": 1.523239314611521,
            "erry-ble": 0.4453044309125399,
            "err-ble": 1.5869952885149083
        },
        {
            "x-coord": 13,
            "y-coord": 2,
            "errx-ble": 0.45655492203134407,
            "erry-ble": 1.9523123366566013,
            "err-ble": 2.0049852509912895
        },
        {
            "x-coord": 25,
            "y-coord": 34,
            "errx-ble": 2.1597356071174736,
            "erry-ble": 3.505099700283909,
            "err-ble": 4.117059849161952
        },
        {
            "x-coord": 7,
            "y-coord": 18,
            "errx-ble": 1.2612062791192455,
            "erry-ble": 1.1862954627269928,
            "err-ble": 1.73145551585262
        },
        {
            "x-coord": 1,
            "y-coord": 2,
            "errx-ble": 3.5415935068021,
            "erry-ble": 3.2232846944459586,
            "err-ble": 4.788783643982298
        },
        {
            "x-coord": 7,
            "y-coord": 34,
            "errx-ble": 1.9981325783337034,
            "erry-ble": 3.757695728457039,
            "err-ble": 4.255914823896593
        },
        {
            "x-coord": 1,
            "y-coord": 10,
            "errx-ble": 3.1837489372357974,
            "erry-ble": 0.6540897283467292,
            "err-ble": 3.2502447089532764
        },
        {
            "x-coord": 19,
            "y-coord": 40,
            "errx-ble": 1.3413628167296205,
            "erry-ble": 6.57904210157576,
            "err-ble": 6.714391199536352
        },
        {
            "x-coord": 25,
            "y-coord": 10,
            "errx-ble": 3.240746626261779,
            "erry-ble": 0.8413517122955211,
            "err-ble": 3.348180311663293
        },
        {
            "x-coord": 19,
            "y-coord": 10,
            "errx-ble": 1.8347836493838248,
            "erry-ble": 0.4210454440186822,
            "err-ble": 1.8824745166867771
        },
        {
            "x-coord": 1,
            "y-coord": 34,
            "errx-ble": 3.0700492117635227,
            "erry-ble": 4.906219106709402,
            "err-ble": 5.787589142785642
        },
        {
            "x-coord": 13,
            "y-coord": 18,
            "errx-ble": 0.15979135025231309,
            "erry-ble": 1.487339542747584,
            "err-ble": 1.4958984561246293
        },
        {
            "x-coord": 7,
            "y-coord": 40,
            "errx-ble": 1.0782187517605815,
            "erry-ble": 4.318883976385992,
            "err-ble": 4.451439596145479
        },
        {
            "x-coord": 7,
            "y-coord": 26,
            "errx-ble": 1.8212242009463182,
            "erry-ble": 2.0655658517562148,
            "err-ble": 2.753800987372532
        },
        {
            "x-coord": 13,
            "y-coord": 26,
            "errx-ble": 0.726390630991926,
            "erry-ble": 0.6493582121377465,
            "err-ble": 0.9743251184607625
        }
    ],
    "mae-ble": 3.3642353386985246,
    "rmse-ble-x": 2.240179232283546,
    "rmse-ble-y": 2.9837911071917373,
    "max-error-ble": 6.714391199536352,
    "min-error-ble": 0.9743251184607625,
    "k": 6,
    "fd": 7,
    "filter": "movingAverage"
}