{
    "beacon": [
        {
            "x-coord": 13,
            "y-coord": 57,
            "beaconData": [
                {
                    "id3": 2,
                    "address": "0C:F3:EE:B5:B2:9E",
                    "rssi": -93.19722094231999,
                    "distance": 2.030888946769859
                },
                {
                    "id3": 8,
                    "address": "0C:F3:EE:B5:B3:6C",
                    "rssi": -74.67601125488727,
                    "distance": 1.2239524797861983
                },
                {
                    "id3": 7,
                    "address": "0C:F3:EE:B5:B3:C8",
                    "rssi": -82.681718622764,
                    "distance": 1.6826961609638915
                },
                {
                    "id3": 4,
                    "address": "0C:F3:EE:B5:BB:20",
                    "rssi": -84.22971388422611,
                    "distance": 2.3868838916295014
                },
                {
                    "id3": 10,
                    "address": "0C:F3:EE:B5:BA:C6",
                    "rssi": -72.24196698226918,
                    "distance": 1.6644986012466534
                },
                {
                    "id3": 3,
                    "address": "0C:F3:EE:B5:BB:22",
                    "rssi": -87.79318746581345,
                    "distance": 2.016992294265922
                },
                {
                    "id3": 1,
                    "address": "0C:F3:EE:B5:B3:B9",
                    "rssi": -92.74985420303511,
                    "distance": 1.6847495980097247
                },
                {
                    "id3": 5,
                    "address": "0C:F3:EE:B5:BB:10",
                    "rssi": -82.62669270938663,
                    "distance": 2.210692295121076
                },
                {
                    "id3": 6,
                    "address": "0C:F3:EE:B5:BB:3F",
                    "rssi": -74.6380859072757,
                    "distance": 4.132008770274218
                },
                {
                    "id3": 9,
                    "address": "0C:F3:EE:B5:BB:2F",
                    "rssi": -53.615448054644695,
                    "distance": 1.130248797719854
                }
            ]
        },
        {
            "x-coord": 27,
            "y-coord": 45,
            "beaconData": [
                {
                    "id3": 2,
                    "address": "0C:F3:EE:B5:B2:9E",
                    "rssi": -88.12017609535513,
                    "distance": 1.6589900562952675
                },
                {
                    "id3": 8,
                    "address": "0C:F3:EE:B5:B3:6C",
                    "rssi": -76.50819503102072,
                    "distance": 1.91491051289121
                },
                {
                    "id3": 7,
                    "address": "0C:F3:EE:B5:B3:C8",
                    "rssi": -84.01993516645409,
                    "distance": 1.5520874091335322
                },
                {
                    "id3": 3,
                    "address": "0C:F3:EE:B5:BB:22",
                    "rssi": -79.62096267389593,
                    "distance": 0.9256866851693444
                },
                {
                    "id3": 4,
                    "address": "0C:F3:EE:B5:BB:20",
                    "rssi": -80.31532149608589,
                    "distance": 0.9067422903866814
                },
                {
                    "id3": 10,
                    "address": "0C:F3:EE:B5:BA:C6",
                    "rssi": -80.87006179334406,
                    "distance": 6.117402319024163
                },
                {
                    "id3": 1,
                    "address": "0C:F3:EE:B5:B3:B9",
                    "rssi": -87.98131321239221,
                    "distance": 1.6251554475895984
                },
                {
                    "id3": 5,
                    "address": "0C:F3:EE:B5:BB:10",
                    "rssi": -61.306194009241516,
                    "distance": 0.7065179413493189
                },
                {
                    "id3": 6,
                    "address": "0C:F3:EE:B5:BB:3F",
                    "rssi": -70.72584550859436,
                    "distance": 2.196732808980312
                },
                {
                    "id3": 9,
                    "address": "0C:F3:EE:B5:BB:2F",
                    "rssi": -78.04488859900408,
                    "distance": 4.2643304033025045
                }
            ]
        },
        {
            "x-coord": 5,
            "y-coord": 57,
            "beaconData": [
                {
                    "id3": 5,
                    "address": "0C:F3:EE:B5:BB:10",
                    "rssi": -77.9166259222759,
                    "distance": 2.071696351209829
                },
                {
                    "id3": 7,
                    "address": "0C:F3:EE:B5:B3:C8",
                    "rssi": -73.076623933199,
                    "distance": 1.4724540118840963
                },
                {
                    "id3": 1,
                    "address": "0C:F3:EE:B5:B3:B9",
                    "rssi": -85.66689476541686,
                    "distance": 1.7956451855583833
                },
                {
                    "id3": 3,
                    "address": "0C:F3:EE:B5:BB:22",
                    "rssi": -81.2699198889052,
                    "distance": 2.1980974293558506
                },
                {
                    "id3": 9,
                    "address": "0C:F3:EE:B5:BB:2F",
                    "rssi": -65.9836015064712,
                    "distance": 1.9105420205437287
                },
                {
                    "id3": 8,
                    "address": "0C:F3:EE:B5:B3:6C",
                    "rssi": -73.41815580734954,
                    "distance": 1.4518892179691334
                },
                {
                    "id3": 2,
                    "address": "0C:F3:EE:B5:B2:9E",
                    "rssi": -84.89351819384252,
                    "distance": 1.819728757089812
                },
                {
                    "id3": 4,
                    "address": "0C:F3:EE:B5:BB:20",
                    "rssi": -75.14042631588732,
                    "distance": 1.8892933158437897
                },
                {
                    "id3": 10,
                    "address": "0C:F3:EE:B5:BA:C6",
                    "rssi": -43.55779713471201,
                    "distance": 1.4706564443505994
                },
                {
                    "id3": 6,
                    "address": "0C:F3:EE:B5:BB:3F",
                    "rssi": -67.84437898752856,
                    "distance": 4.003043079409081
                }
            ]
        },
        {
            "x-coord": 1,
            "y-coord": 45,
            "beaconData": [
                {
                    "id3": 10,
                    "address": "0C:F3:EE:B5:BA:C6",
                    "rssi": -69.80781958401023,
                    "distance": 3.0921968684019037
                },
                {
                    "id3": 6,
                    "address": "0C:F3:EE:B5:BB:3F",
                    "rssi": -65.24581997479466,
                    "distance": 2.3058725257987573
                },
                {
                    "id3": 7,
                    "address": "0C:F3:EE:B5:B3:C8",
                    "rssi": -61.80199948991108,
                    "distance": 0.7800232529061717
                },
                {
                    "id3": 2,
                    "address": "0C:F3:EE:B5:B2:9E",
                    "rssi": -84.10966620611154,
                    "distance": 1.5329082328540398
                },
                {
                    "id3": 1,
                    "address": "0C:F3:EE:B5:B3:B9",
                    "rssi": -84.30098672757669,
                    "distance": 1.4588180264171537
                },
                {
                    "id3": 8,
                    "address": "0C:F3:EE:B5:B3:6C",
                    "rssi": -78.63855528630849,
                    "distance": 1.9851656779379994
                },
                {
                    "id3": 3,
                    "address": "0C:F3:EE:B5:BB:22",
                    "rssi": -80.80077688358875,
                    "distance": 1.3700654464048274
                },
                {
                    "id3": 9,
                    "address": "0C:F3:EE:B5:BB:2F",
                    "rssi": -76.07062320087803,
                    "distance": 4.1643821578421125
                },
                {
                    "id3": 4,
                    "address": "0C:F3:EE:B5:BB:20",
                    "rssi": -73.58006261386292,
                    "distance": 1.6594724348608973
                },
                {
                    "id3": 5,
                    "address": "0C:F3:EE:B5:BB:10",
                    "rssi": -78.41549744216947,
                    "distance": 2.1820077964818334
                }
            ]
        },
        {
            "x-coord": 13,
            "y-coord": 45,
            "beaconData": [
                {
                    "id3": 2,
                    "address": "0C:F3:EE:B5:B2:9E",
                    "rssi": -89.9835631415825,
                    "distance": 1.5363036737072404
                },
                {
                    "id3": 8,
                    "address": "0C:F3:EE:B5:B3:6C",
                    "rssi": -80.18790303362239,
                    "distance": 1.5625580503965575
                },
                {
                    "id3": 7,
                    "address": "0C:F3:EE:B5:B3:C8",
                    "rssi": -78.65784344845582,
                    "distance": 1.0819717311493955
                },
                {
                    "id3": 3,
                    "address": "0C:F3:EE:B5:BB:22",
                    "rssi": -84.7211482033877,
                    "distance": 0.8094616717894647
                },
                {
                    "id3": 4,
                    "address": "0C:F3:EE:B5:BB:20",
                    "rssi": -80.66805231818508,
                    "distance": 1.640644529260276
                },
                {
                    "id3": 10,
                    "address": "0C:F3:EE:B5:BA:C6",
                    "rssi": -78.52370633864943,
                    "distance": 4.881489706410185
                },
                {
                    "id3": 1,
                    "address": "0C:F3:EE:B5:B3:B9",
                    "rssi": -90.66277580857881,
                    "distance": 1.1393111296056404
                },
                {
                    "id3": 5,
                    "address": "0C:F3:EE:B5:BB:10",
                    "rssi": -78.49929535364704,
                    "distance": 1.6913210573669604
                },
                {
                    "id3": 6,
                    "address": "0C:F3:EE:B5:BB:3F",
                    "rssi": -59.765378006925495,
                    "distance": 1.4607110277926305
                },
                {
                    "id3": 9,
                    "address": "0C:F3:EE:B5:BB:2F",
                    "rssi": -77.05009558614009,
                    "distance": 1.2080883498079884
                }
            ]
        },
        {
            "x-coord": 23,
            "y-coord": 57,
            "beaconData": [
                {
                    "id3": 2,
                    "address": "0C:F3:EE:B5:B2:9E",
                    "rssi": -86.71660096282102,
                    "distance": 2.077051045613603
                },
                {
                    "id3": 8,
                    "address": "0C:F3:EE:B5:B3:6C",
                    "rssi": -47.9006784331709,
                    "distance": 0.12339892835593344
                },
                {
                    "id3": 7,
                    "address": "0C:F3:EE:B5:B3:C8",
                    "rssi": -79.2905675434886,
                    "distance": 2.238340051962334
                },
                {
                    "id3": 10,
                    "address": "0C:F3:EE:B5:BA:C6",
                    "rssi": -73.30695996908219,
                    "distance": 2.366514932166152
                },
                {
                    "id3": 3,
                    "address": "0C:F3:EE:B5:BB:22",
                    "rssi": -80.49077663425882,
                    "distance": 1.3160633638186625
                },
                {
                    "id3": 4,
                    "address": "0C:F3:EE:B5:BB:20",
                    "rssi": -78.24049487937097,
                    "distance": 2.1600695747809255
                },
                {
                    "id3": 1,
                    "address": "0C:F3:EE:B5:B3:B9",
                    "rssi": -86.2846803218338,
                    "distance": 1.6530702725940551
                },
                {
                    "id3": 5,
                    "address": "0C:F3:EE:B5:BB:10",
                    "rssi": -72.21542948631456,
                    "distance": 1.844804760881709
                },
                {
                    "id3": 6,
                    "address": "0C:F3:EE:B5:BB:3F",
                    "rssi": -69.0702382461554,
                    "distance": 3.992226857987491
                },
                {
                    "id3": 9,
                    "address": "0C:F3:EE:B5:BB:2F",
                    "rssi": -65.4957472481154,
                    "distance": 1.0729302516305599
                }
            ]
        }
    ]
}